email_helper/__init__.py
email_helper/email_receiver.py
email_helper/email_sender.py
email_helper-0.0.4.dist-info/DESCRIPTION.rst
email_helper-0.0.4.dist-info/METADATA
email_helper-0.0.4.dist-info/RECORD
email_helper-0.0.4.dist-info/WHEEL
email_helper-0.0.4.dist-info/metadata.json
email_helper-0.0.4.dist-info/top_level.txt
