Metadata-Version: 2.0
Name: email-helper
Version: 0.0.4
Summary: email helper for simple send email and receive email of python
Home-page: https://github.com/mouday/email_helper
Author: Peng Shiyu
Author-email: pengshiyuyx@gmail.com
License: UNKNOWN
Platform: UNKNOWN
Classifier: Programming Language :: Python :: 3
Classifier: License :: OSI Approved :: MIT License
Classifier: Operating System :: OS Independent
